hkvwaporpy/__init__.py
hkvwaporpy/fao_wapor_api.py
hkvwaporpy/hkvwapory.code-workspace
hkvwaporpy-0.7.2.dist-info/LICENSE
hkvwaporpy-0.7.2.dist-info/WHEEL
hkvwaporpy-0.7.2.dist-info/METADATA
hkvwaporpy-0.7.2.dist-info/RECORD
