Metadata-Version: 2.1
Name: hkvwaporpy
Version: 0.7.2
Summary: package for FAO WAPOR API
Home-page: https://github.com/HKV-products-services/hkvwaporpy
License: UNKNOWN
Author: Mattijn van Hoek
Author-email: hoek@hkv.nl
Classifier: License :: OSI Approved :: GNU General Public License v3 or later (GPLv3+)
